aiopeewee/__init__.py
aiopeewee/_compat.py
aiopeewee/py.typed
aiopeewee/transactions.py
aio_peewee-0.4.1.dist-info/LICENSE
aio_peewee-0.4.1.dist-info/METADATA
aio_peewee-0.4.1.dist-info/WHEEL
aio_peewee-0.4.1.dist-info/top_level.txt
aio_peewee-0.4.1.dist-info/RECORD
