Metadata-Version: 2.1
Name: aio-peewee
Version: 0.4.1
Summary: Peewee support for async frameworks (Asyncio, Trio)
Home-page: https://github.com/klen/aio-peewee
Author: Kirill Klenov
Author-email: horneds@gmail.com
License: MIT
Project-URL: Documentation, https://github.com/klen/aio-peewee
Project-URL: Source code, https://github.com/klen/aio-peewee
Project-URL: Issue tracker, https://github.com/klen/aio-peewee/issues
Keywords: peewee,asyncio,trio,asgi
Platform: UNKNOWN
Classifier: Development Status :: 5 - Production/Stable
Classifier: Intended Audience :: Developers
Classifier: License :: OSI Approved :: MIT License
Classifier: Programming Language :: Python
Classifier: Programming Language :: Python :: 3
Classifier: Programming Language :: Python :: 3.7
Classifier: Programming Language :: Python :: 3.8
Classifier: Programming Language :: Python :: 3.9
Classifier: Framework :: AsyncIO
Classifier: Framework :: Trio
Requires-Python: >=3.7
License-File: LICENSE
Requires-Dist: peewee (>3)
Requires-Dist: sniffio
Provides-Extra: tests
Requires-Dist: asgi-tools (>=0.40) ; extra == 'tests'
Requires-Dist: pytest ; extra == 'tests'
Requires-Dist: pytest-mypy ; extra == 'tests'
Requires-Dist: pytest-aio[curio,trio] ; extra == 'tests'
